Workbook

Sheet Bridge_Inputs
A1: NOI → AFFO Bridge — Inputs
A3: Assumption | B3: Q1 Base | C3: Q1 Upside | D3: Q1 Downside | E3: Year Base | F3: Year Upside | G3: Year Downside
A4: Cash NOI (pre-amort.) | B4: 27280.856 | C4: 29702.941 | D4: -23186.764 | E4: 386003.47 | F4: 404134.06 | G4: 315479.61
A5: TI Amortization (negative) | B5: -10000 | C5: -10000 | D5: -10000 | E5: -40000 | F5: -40000 | G5: -40000
A6: LC Amortization (negative) | B6: -6145.8333 | C6: -6145.8333 | D6: -6145.8333 | E6: -24583.333 | F6: -24583.333 | G6: -24583.333
A7: Corporate G&A (if alloc.) | B7: 0 | C7: 0 | D7: 0 | E7: 0 | F7: 0 | G7: 0
A8: Management Fee (if any) | B8: 0 | C8: 0 | D8: 0 | E8: 0 | F8: 0 | G8: 0
A9: Other Op. Adj. (non-cash) | B9: 0 | C9: 0 | D9: 0 | E9: 0 | F9: 0 | G9: 0
A10: Interest Expense (negative) | B10: -78125 | C10: -78125 | D10: -78125 | E10: -312500 | F10: -312500 | G10: -312500
A11: Recurring Capex (cash) | B11: 0 | C11: 0 | D11: 0 | E11: 0 | F11: 0 | G11: 0
A12: Straight-line Rent Adj. | B12: 0 | C12: 0 | D12: 0 | E12: 0 | F12: 0 | G12: 0
A13: Leasing Costs (cash) | B13: 0 | C13: 0 | D13: 0 | E13: 0 | F13: 0 | G13: 0
A15: Notes:
A16: • Paste NOI(pre-amort.) from Lease→NOI; negatives reduce AFFO.
A17: • Replace Interest with debt schedule outputs when available.

Sheet Bridge_Calc
B1: Consolidated Bridge
A3: Bridge Item | C3: Q1 Base | D3: Q1 Upside | E3: Q1 Downside | F3: Year Base | G3: Year Upside | H3: Year Downside
A4: NOI → (EBITDAre) → FFO → AFFO
B5: Cash NOI (pre-amort.) | C5: =Bridge_Inputs!B4 -> 27280.856 | D5: =Bridge_Inputs!C4 -> 29702.941 | E5: =Bridge_Inputs!D4 -> -23186.764 | F5: =Bridge_Inputs!E4 -> 386003.47 | G5: =Bridge_Inputs!F4 -> 404134.06 | H5: =Bridge_Inputs!G4 -> 315479.61
B6: + TI Amortization | C6: =Bridge_Inputs!B5 -> -10000 | D6: =Bridge_Inputs!C5 -> -10000 | E6: =Bridge_Inputs!D5 -> -10000 | F6: =Bridge_Inputs!E5 -> -40000 | G6: =Bridge_Inputs!F5 -> -40000 | H6: =Bridge_Inputs!G5 -> -40000
B7: + LC Amortization | C7: =Bridge_Inputs!B6 -> -6145.8333 | D7: =Bridge_Inputs!C6 -> -6145.8333 | E7: =Bridge_Inputs!D6 -> -6145.8333 | F7: =Bridge_Inputs!E6 -> -24583.333 | G7: =Bridge_Inputs!F6 -> -24583.333 | H7: =Bridge_Inputs!G6 -> -24583.333
B8: NOI | C8: =SUM(C5:C7) -> 11135.023 | D8: =SUM(D5:D7) -> 13557.107 | E8: =SUM(E5:E7) -> -39332.597 | F8: =SUM(F5:F7) -> 321420.13 | G8: =SUM(G5:G7) -> 339550.72 | H8: =SUM(H5:H7) -> 250896.28
B10: - Corporate G&A | C10: =Bridge_Inputs!B7 -> 0 | D10: =Bridge_Inputs!C7 -> 0 | E10: =Bridge_Inputs!D7 -> 0 | F10: =Bridge_Inputs!E7 -> 0 | G10: =Bridge_Inputs!F7 -> 0 | H10: =Bridge_Inputs!G7 -> 0
B11: - Management Fee | C11: =Bridge_Inputs!B8 -> 0 | D11: =Bridge_Inputs!C8 -> 0 | E11: =Bridge_Inputs!D8 -> 0 | F11: =Bridge_Inputs!E8 -> 0 | G11: =Bridge_Inputs!F8 -> 0 | H11: =Bridge_Inputs!G8 -> 0
B12: ± Other Operating Adj. | C12: =Bridge_Inputs!B9 -> 0 | D12: =Bridge_Inputs!C9 -> 0 | E12: =Bridge_Inputs!D9 -> 0 | F12: =Bridge_Inputs!E9 -> 0 | G12: =Bridge_Inputs!F9 -> 0 | H12: =Bridge_Inputs!G9 -> 0
B13: - Interest Expense | C13: =Bridge_Inputs!B10 -> -78125 | D13: =Bridge_Inputs!C10 -> -78125 | E13: =Bridge_Inputs!D10 -> -78125 | F13: =Bridge_Inputs!E10 -> -312500 | G13: =Bridge_Inputs!F10 -> -312500 | H13: =Bridge_Inputs!G10 -> -312500
B14: FFO (light) | C14: =SUM(C8:C13) -> -66989.977 | D14: =SUM(D8:D13) -> -64567.893 | E14: =SUM(E8:E13) -> -117457.6 | F14: =SUM(F8:F13) -> 8920.1337 | G14: =SUM(G8:G13) -> 27050.723 | H14: =SUM(H8:H13) -> -61603.723
B16: - Recurring Capex | C16: =Bridge_Inputs!B11 -> 0 | D16: =Bridge_Inputs!C11 -> 0 | E16: =Bridge_Inputs!D11 -> 0 | F16: =Bridge_Inputs!E11 -> 0 | G16: =Bridge_Inputs!F11 -> 0 | H16: =Bridge_Inputs!G11 -> 0
B17: ± Straight-line Rent | C17: =Bridge_Inputs!B12 -> 0 | D17: =Bridge_Inputs!C12 -> 0 | E17: =Bridge_Inputs!D12 -> 0 | F17: =Bridge_Inputs!E12 -> 0 | G17: =Bridge_Inputs!F12 -> 0 | H17: =Bridge_Inputs!G12 -> 0
B18: - TI/LC (cash) | C18: =Bridge_Inputs!B13 -> 0 | D18: =Bridge_Inputs!C13 -> 0 | E18: =Bridge_Inputs!D13 -> 0 | F18: =Bridge_Inputs!E13 -> 0 | G18: =Bridge_Inputs!F13 -> 0 | H18: =Bridge_Inputs!G13 -> 0
B19: AFFO | C19: =SUM(C14:C18) -> -66989.977 | D19: =SUM(D14:D18) -> -64567.893 | E19: =SUM(E14:E18) -> -117457.6 | F19: =SUM(F14:F18) -> 8920.1337 | G19: =SUM(G14:G18) -> 27050.723 | H19: =SUM(H14:H18) -> -61603.723

Sheet EBITDAre
A1: EBITDAre
A2: (NOI minus corporate items)
A4: Item | B4: Q1 Base | C4: Q1 Upside | D4: Q1 Downside | E4: Year Base | F4: Year Upside | G4: Year Downside
A5: NOI | B5: =SUM(Bridge_Inputs!B4:B6) -> 11135.023 | C5: =SUM(Bridge_Inputs!C4:C6) -> 13557.107 | D5: =SUM(Bridge_Inputs!D4:D6) -> -39332.597 | E5: =SUM(Bridge_Inputs!E4:E6) -> 321420.13 | F5: =SUM(Bridge_Inputs!F4:F6) -> 339550.72 | G5: =SUM(Bridge_Inputs!G4:G6) -> 250896.28
A6: - Corporate G&A | B6: =Bridge_Inputs!B7 -> 0 | C6: =Bridge_Inputs!C7 -> 0 | D6: =Bridge_Inputs!D7 -> 0 | E6: =Bridge_Inputs!E7 -> 0 | F6: =Bridge_Inputs!F7 -> 0 | G6: =Bridge_Inputs!G7 -> 0
A7: - Management Fee | B7: =Bridge_Inputs!B8 -> 0 | C7: =Bridge_Inputs!C8 -> 0 | D7: =Bridge_Inputs!D8 -> 0 | E7: =Bridge_Inputs!E8 -> 0 | F7: =Bridge_Inputs!F8 -> 0 | G7: =Bridge_Inputs!G8 -> 0
A8: ± Other Op. Adj. | B8: =Bridge_Inputs!B9 -> 0 | C8: =Bridge_Inputs!C9 -> 0 | D8: =Bridge_Inputs!D9 -> 0 | E8: =Bridge_Inputs!E9 -> 0 | F8: =Bridge_Inputs!F9 -> 0 | G8: =Bridge_Inputs!G9 -> 0
A9: EBITDAre | B9: =SUM(B5:B8) -> 11135.023 | C9: =SUM(C5:C8) -> 13557.107 | D9: =SUM(D5:D8) -> -39332.597 | E9: =SUM(E5:E8) -> 321420.13 | F9: =SUM(F5:F8) -> 339550.72 | G9: =SUM(G5:G8) -> 250896.28

Sheet FFO_Bridge
A1: FFO Bridge
A2: (EBITDAre → FFO)
A4: Item | B4: Q1 Base | C4: Q1 Upside | D4: Q1 Downside | E4: Year Base | F4: Year Upside | G4: Year Downside
A5: EBITDAre | B5: =EBITDAre!B9 -> 11135.023 | C5: =EBITDAre!C9 -> 13557.107 | D5: =EBITDAre!D9 -> -39332.597 | E5: =EBITDAre!E9 -> 321420.13 | F5: =EBITDAre!F9 -> 339550.72 | G5: =EBITDAre!G9 -> 250896.28
A6: - Interest Expense | B6: =Bridge_Inputs!B10 -> -78125 | C6: =Bridge_Inputs!C10 -> -78125 | D6: =Bridge_Inputs!D10 -> -78125 | E6: =Bridge_Inputs!E10 -> -312500 | F6: =Bridge_Inputs!F10 -> -312500 | G6: =Bridge_Inputs!G10 -> -312500
A7: + Depreciation & Amort. | B7: 0 | C7: 0 | D7: 0 | E7: 0 | F7: 0 | G7: 0
A8: ± Non-recurring Adj. | B8: 0 | C8: 0 | D8: 0 | E8: 0 | F8: 0 | G8: 0
A9: FFO (light) | B9: =SUM(B5:B8) -> -66989.977 | C9: =SUM(C5:C8) -> -64567.893 | D9: =SUM(D5:D8) -> -117457.6 | E9: =SUM(E5:E8) -> 8920.1337 | F9: =SUM(F5:F8) -> 27050.723 | G9: =SUM(G5:G8) -> -61603.723

Sheet AFFO_Bridge
A1: AFFO Bridge
A2: (FFO → AFFO)
A4: Item | B4: Q1 Base | C4: Q1 Upside | D4: Q1 Downside | E4: Year Base | F4: Year Upside | G4: Year Downside
A5: FFO (light) | B5: =FFO_Bridge!B9 -> -66989.977 | C5: =FFO_Bridge!C9 -> -64567.893 | D5: =FFO_Bridge!D9 -> -117457.6 | E5: =FFO_Bridge!E9 -> 8920.1337 | F5: =FFO_Bridge!F9 -> 27050.723 | G5: =FFO_Bridge!G9 -> -61603.723
A6: - Recurring Capex (cash) | B6: =Bridge_Inputs!B11 -> 0 | C6: =Bridge_Inputs!C11 -> 0 | D6: =Bridge_Inputs!D11 -> 0 | E6: =Bridge_Inputs!E11 -> 0 | F6: =Bridge_Inputs!F11 -> 0 | G6: =Bridge_Inputs!G11 -> 0
A7: ± Straight-line Rent | B7: =Bridge_Inputs!B12 -> 0 | C7: =Bridge_Inputs!C12 -> 0 | D7: =Bridge_Inputs!D12 -> 0 | E7: =Bridge_Inputs!E12 -> 0 | F7: =Bridge_Inputs!F12 -> 0 | G7: =Bridge_Inputs!G12 -> 0
A8: - TI/LC (cash, if used) | B8: =Bridge_Inputs!B13 -> 0 | C8: =Bridge_Inputs!C13 -> 0 | D8: =Bridge_Inputs!D13 -> 0 | E8: =Bridge_Inputs!E13 -> 0 | F8: =Bridge_Inputs!F13 -> 0 | G8: =Bridge_Inputs!G13 -> 0
A9: AFFO | B9: =SUM(B5:B8) -> -66989.977 | C9: =SUM(C5:C8) -> -64567.893 | D9: =SUM(D5:D8) -> -117457.6 | E9: =SUM(E5:E8) -> 8920.1337 | F9: =SUM(F5:F8) -> 27050.723 | G9: =SUM(G5:G8) -> -61603.723

Sheet Coverage
A1: Dividend Coverage — Policy & Outputs
A2: prioritise Payout policy | G2: MAX(policy,override)
G3: MIN(policy,override)
A4: Assumption | B4: Base | C4: Upside | D4: Downside
A5: Units / Shares Outstanding | B5: 1000000 | C5: 1000000 | D5: 1000000
A6: Payout policy (% of AFFO) | B6: 0.8 | C6: 0.8 | D6: 0.8
A7: Target Dividend per unit (override, $) | B7: 0.25 | C7: 0.25 | D7: 0.25
A10: Metric | B10: Base | C10: Upside | D10: Downside
A11: AFFO (Year) | B11: =Bridge_Calc!F19 -> 8920.1337 | C11: =Bridge_Calc!G19 -> 27050.723 | D11: =Bridge_Calc!H19 -> -61603.723
A12: AFFO / unit | B12: =IF(B5=0,0,B11/B5) -> 0.0089201337 | C12: =IF(C5=0,0,C11/C5) -> 0.027050723 | D12: =IF(D5=0,0,D11/D5) -> -0.061603723
A13: Dividend / unit | B13: =IF(B12>0,MIN(B6*B12,B7),0) -> 0.0071361069 | C13: =IF(C12>0,MIN(C6*C12,C7),0) -> 0.021640578 | D13: =IF(D12>0,MIN(D6*D12,D7),0) -> 0
A14: Coverage (AFFO / Dividend) | B14: =IF(OR(B11<0,B13<0),0,B12/B13) -> 1.25 | C14: =IF(OR(C11<0,C13<0),0,C12/C13) -> 1.25 | D14: =IF(OR(D11<0,D13<0),0,D12/D13) -> 0
B15: =IF(B13/B12>1, "⚠️ Over-distribution", "OK") -> OK | C15: =IF(C13/C12>1, "⚠️ Over-distribution", "OK") -> OK | D15: =IF(D13/D12>1, "⚠️ Over-distribution", "OK") -> OK

Sheet Bridge_Chart
A1: NOI → AFFO Waterfall (Year, Base)
A3: Item | B3: Amount
A4: Cash NOI (pre-amort.) | B4: =Bridge_Calc!F5 -> 386003.47
A5: TI Amort. | B5: =Bridge_Calc!F6 -> -40000
A6: LC Amort. | B6: =Bridge_Calc!F7 -> -24583.333
A7: NOI | B7: =Bridge_Calc!F8 -> 321420.13
A8: G&A | B8: =Bridge_Calc!F10 -> 0
A9: Mgmt Fee | B9: =Bridge_Calc!F11 -> 0
A10: Other Op.Adj. | B10: =Bridge_Calc!F12 -> 0
A11: Interest | B11: =Bridge_Calc!F13 -> -312500
A12: FFO (light) | B12: =Bridge_Calc!F14 -> 8920.1337
A13: Recurring Capex | B13: =Bridge_Calc!F16 -> 0
A14: Straight-line Adj. | B14: =Bridge_Calc!F17 -> 0
A15: Leasing Costs | B15: =Bridge_Calc!F18 -> 0
A16: AFFO | B16: =Bridge_Calc!F19 -> 8920.1337

Sheet Dictionary
A1: Field Dictionary (NOI → EBITDAre → FFO → AFFO)
A3: Field | B3: Definition / Treatment | C3: Unit | D3: Sheet
A4: Cash NOI (pre-amort.) | B4: Paste from Lease→NOI (cash NOI before TI/LC amort.) | C4: $ | D4: Bridge_Inputs
A5: TI Amortization | B5: Evenly amortized tenant improvements (negative) | C5: $ | D5: Bridge_Inputs
A6: LC Amortization | B6: Evenly amortized leasing commissions (negative) | C6: $ | D6: Bridge_Inputs
A7: Corporate G&A | B7: Allocated corporate overhead; if any | C7: $ | D7: Bridge_Inputs
A8: Management Fee | B8: Property management fee; % of rent/NOI | C8: $ | D8: Bridge_Inputs
A9: Other Op. Adj. | B9: Recurring operating adjustments (often 0 in light version) | C9: $ | D9: Bridge_Inputs
A10: Interest Expense | B10: Debt cost with hedge mix | C10: $ | D10: Bridge_Inputs
A11: Recurring Capex | B11: Maintenance CapEx | C11: $ | D11: Bridge_Inputs
A12: Straight-line Rent | B12: Adjustment to cash basis if required | C12: $ | D12: Bridge_Inputs
A13: LC/TI (cash) | B13: Cash leasing costs if cash-based disclosure is used | C13: $ | D13: Bridge_Inputs
A14: EBITDAre | B14: NOI – G&A – Mgmt Fee ± Op.Adj. | C14: $ | D14: EBITDAre
... A18: Coverage | B18: AFFO / Dividend | C18: x | D18: Coverage
